MANIFEST.in
README.md
requirements.txt
setup.cfg
setup.py
forest/__init__.py
forest/apps.py
forest/urls.py
forest/generators/__init__.py
forest/generators/schemas.py
forest/serializers/__init__.py
forest/serializers/inflector.py
forest/serializers/resource.py
forest/serializers/serializer.py
forest/serializers/serializer_utils.py
forest/serializers/stat.py
forest/serializers/stripe.py
forest/services/__init__.py
forest/services/allowed_user_getter.py
forest/services/filter_generator.py
forest/services/has_many_getter.py
forest/services/line_stat_getter.py
forest/services/operator_date_interval_parser.py
forest/services/pie_stat_getter.py
forest/services/resource_creator.py
forest/services/resource_getter.py
forest/services/resource_remover.py
forest/services/resource_updater.py
forest/services/resources_getter.py
forest/services/stripe_payments_getter.py
forest/services/utils.py
forest/services/value_stat_getter.py
forest/views/__init__.py
forest/views/association.py
forest/views/empty.py
forest/views/resource.py
forest/views/resources.py
forest/views/session.py
forest/views/stat.py
forest/views/stripe.py
forest_django.egg-info/PKG-INFO
forest_django.egg-info/SOURCES.txt
forest_django.egg-info/dependency_links.txt
forest_django.egg-info/requires.txt
forest_django.egg-info/top_level.txt